ableton_helpers/__init__.py
ableton_helpers/change_version/__init__.py
ableton_helpers/change_version/example_als/all-tracks-set-11-1-5.als
ableton_helpers/change_version/example_als/all-tracks-set.als
ableton_helpers/change_version/run.py
ableton_helpers/change_version/versions_info.json
ableton_helpers-0.1.0.dist-info/WHEEL
ableton_helpers-0.1.0.dist-info/entry_points.txt
ableton_helpers-0.1.0.dist-info/METADATA
ableton_helpers-0.1.0.dist-info/RECORD
